Metadata-Version: 2.1
Name: backwards_regression
Version: 0.1.0
Summary: Backwards Regression Python Library - Automated feature selection in linear and logistic regression models.
Home-page: https://github.com/knowusuboaky/backwards_regression
Author: Kwadwo Daddy Nyame Owusu - Boakye
Author-email: kwadwo.owusuboakye@outlook.com
License: MIT
Keywords: statistics modeling regression feature elimination engineering
Classifier: License :: OSI Approved :: MIT License
Classifier: Programming Language :: Python :: 3
Classifier: Programming Language :: Python :: 3.6
Classifier: Programming Language :: Python :: 3.7
Classifier: Programming Language :: Python :: 3.8
Classifier: Programming Language :: Python :: 3.9
Classifier: Programming Language :: Python :: 3.10
Classifier: Programming Language :: Python :: 3.11
Classifier: Programming Language :: Python :: 3.12
Requires-Python: >=3.7
License-File: LICENSE.txt
Requires-Dist: pandas
Requires-Dist: statsmodels
